batsaevtest/__init__.py
batsaevtest/examples.py
batsaevtest-0.0.1.dist-info/METADATA
batsaevtest-0.0.1.dist-info/WHEEL
batsaevtest-0.0.1.dist-info/top_level.txt
batsaevtest-0.0.1.dist-info/RECORD
