Metadata-Version: 2.1
Name: batsaevtest
Version: 0.0.1
Summary: Work
Home-page: https://github.com/saiyan05122004
Author: Abdula Batsaev
Author-email: abdyla05122004@gmail.com
Project-URL: GitHub, https://github.com/saiyan05122004
Keywords: files speedfiles
Classifier: Programming Language :: Python :: 3.11
Classifier: License :: OSI Approved :: MIT License
Classifier: Operating System :: OS Independent
Requires-Python: >=3.6
Requires-Dist: requests >=2.25.1
